sklearn_ex/__init__.py
sklearn_ex/ensemble/__init__.py
sklearn_ex/ensemble/_forest.py
sklearn_ex/tree/__init__.py
sklearn_ex/tree/_classes.py
sklearn_ex-0.0.1.dist-info/METADATA
sklearn_ex-0.0.1.dist-info/WHEEL
sklearn_ex-0.0.1.dist-info/top_level.txt
sklearn_ex-0.0.1.dist-info/RECORD
